{"pkmntcgtrades": {"active": ["fvo43pq", "fvp281m", "fvp4zwz", "fvpfldv", "fvqknpi", "fvsxdoz", "fvt2ex0", "fvumih8", "fvumsca", "fvv41m2", "fvv4fdo", "fvwdu44", "fvyz5b6", "fvz2o1m", "fvzkhy7", "fvzklcn", "fw099af", "fw09n2u", "fw0aljq"], "archived": ["fru3h3l", "frvo47a", "frwu9ov", "frwwcbl", "frxejhd", "fs968ke", "fsmruv5", "ft5g0qc", "fswhm5t", "ft60p2w", "ftglf8j", "ftm4ybb", "ftqo212", "fuov18i", "fuqiyth", "fv4zuou", "fv22ep4", "fv21tn2", "fuxtra3", "fv46dpl", "fuwohdg", "fuy9twg", "fvcizes", "fvese2j", "fv6tmo2", "fv6c9e2", "fvdivnq", "fvefqc8", "fvg7rq8", "fvh7pph", "fvprrla"]}, "steelbookswap": {"active": ["fvpn0gk"], "archived": ["fs9uxcd", "fuxyekn", "fvah9z5"]}, "digitalcodeexchange": {"active": [], "archived": []}, "funkoswap": {"active": ["fvntx4d", "fvpogty", "fvur26g", "fvypn5h"], "archived": ["ft3o654", "ftekcja", "ftiev06", "fuxo50j", "fv0gum9", "fvd8ko1", "fv8ftc7", "fvlz35q"]}, "DisneyStoreKeySwap": {"active": [], "archived": []}, "digitalcodesell": {"active": ["fvndcvc", "fvnr79t", "fvo4vbz", "fvo89or", "fvo8nht", "fvojp7n", "fvooatu", "fvop345", "fvor1c9", "fvorpcg", "fvpdma4", "fvperna", "fvptidv", "fvq4oej", "fvqwz83", "fvr8mc1", "fvrtzhy", "fvsieml", "fvszlr6", "fvt7foa", "fvt8tcm", "fvt9mto", "fvv153f", "fvv27j5", "fvv3s77", "fvvb364", "fvvc6pp", "fvvlhq9", "fvvvd9s", "fvw63nb", "fvw8adf", "fvwckmk", "fvwd8rn", "fvwet94", "fvwngpe", "fvww7at", "fvww65z", "fvww4ks", "fvyozea", "fvyou0h", "fvyr65k", "fvytgvs", "fvz12ga", "fvz4ztl", "fvz5m0n", "fvz8q7q", "fvz8k4g", "fvzbuac", "fvzcefq", "fvzbsys", "fvze3kp", "fvznxsv", "fvznvgl", "fvzpuuq", "fvztyj1", "fvzwfkj", "fvzxwv4", "fvzxw1r", "fvzynlx", "fw08v4k"], "archived": ["frspzx2", "frsz7nn", "frszqyi", "frt0ks6", "frtu8su", "frvr9ll", "frvzibk", "frwtdzu", "frwyel1", "frxmezj", "fryby5m", "frzck3u", "frze0ea", "fs0c5ob", "fs1r90w", "fs1ylor", "fs23czb", "fs419ed", "fs4buq1", "fs59nef", "fs5sr2y", "fs7ujmi", "fs8rnmf", "fs92ixv", "fs98clt", "fsb8ycu", "fscqu96", "fsdmiyv", "fse976y", "fsexacg", "fsfbhmx", "fsg74cs", "fsgyvyk", "fskcm8c", "fskyoed", "fslqqk3", "fslwmqf", "fsmyre0", "fsn25wq", "fsnhkdv", "fso015z", "fso8g4u", "fsorrht", "fspdkqu", "fsrxq3t", "fsrxula", "fssa7n0", "fssavfc", "fssvmqo", "fstcy0o", "fstnx5o", "fsvi69z", "fsvln3a", "fsvnc2b", "fsw0gmo", "fsw199m", "fsw14tq", "fsw2yj4", "fswjf1l", "fsywew2", "fszl7vw", "ft0z6ae", "ft128x6", "ft1ifse", "ft2nvho", "ft5e9z1", "ft6ee7m", "ft6ufww", "ft777pw", "ft782gr", "ftbq5cf", "ftbsob0", "ftc0l3u", "ftc0sq6", "ftc0yu7", "ftc0wa1", "ftd1cfq", "fte3x6w", "fte96m4", "fteokcq", "ftfbmzk", "ftfk0pg", "ftfjyoi", "ftg1td2", "ftgr75a", "ftgrbrb", "ftgrgdj", "ftgripc", "ftgrnij", "ftia1q6", "ftiflp8", "ftjd4xm", "ftjig8z", "ftjunhb", "ftl2pkm", "ftlul5t", "ftluo3b", "ftm2syh", "ftm6z26", "ftmpcb4", "ftnckt3", "fto0zjz", "ftpvvi5", "ftql0u6", "ftqttp6", "ftrldqf", "ftrp5j4", "fumk48h", "fuoiydk", "fuqoa0k", "furjmc0", "furslcj", "fuun0rq", "fv2nhsp", "fuynqig", "fv2334h", "fv2byr4", "fuzdbbj", "fuxn1tn", "fv235ca", "fuxhtkg", "fv5eprd", "fut9cve", "fv3gj0b", "fv2jlk3", "fuzdacy", "fuutbv9", "fv3ri5m", "fuz16bn", "fuxxtqr", "fuzwgu4", "fv2jdni", "fv1bdtt", "fuybsux", "fuv4y8t", "fuzhpny", "fuxpgjh", "fuyq0fw", "fv22x6w", "fv2v793", "fv13ieo", "fv9iavx", "fvdat6b", "fv9k3uj", "fv5vg3h", "fv5ybjd", "fv6zk09", "fv725nh", "fv8lqmp", "fvb2kq2", "fvd1n5t", "fvdj0nw", "fvdzztm", "fvei1je", "fvelrwc", "fvfseqc", "fvfzsqt", "fvg7ogp", "fvgbm0j", "fvhfixs", "fvhjqed", "fvhxvdj", "fvi5ioo", "fvkmgh5", "fvkrzpb", "fvksub1", "fvktv1w", "fvkw2fg", "fvkxunf", "fvl1zyd", "fvl471r", "fvl7r7a", "fvl7w3d", "fvlboc1", "fvlgprr", "fvlhbsv", "fvmy5mq", "fvn821e", "fvnaj1u"]}, "snackexchange": {"active": ["fvnmy3g", "fvotrlj", "fvp6u5d", "fvpb3gv", "fvpfhh5", "fvz91fp", "fvzgpyq"], "archived": ["fs06fm5", "fuzkmu2", "fv6blrm", "fvcoegt", "fvc4w5i", "fv6gq1e", "fvdwqt1", "fvna22b"]}, "bluraysale": {"active": [], "archived": []}, "mousemarket": {"active": ["fvp6w55", "fvp93ui", "fvtaqb1", "fvw9xu1", "fvy25fo", "fvz9fko", "fvzt2br"], "archived": ["frvmq2x", "frxh1pl", "fs1i0n6", "fs4zdoc", "fsqr84z", "fsti59l", "ftdrins", "ftm7ulh", "fuvqwc6", "fuvj2rj", "fv2wrwd", "fv68wcc", "fvcn1d9"]}, "uvtrade": {"active": ["fvowri8", "fvpgtll", "fvprqcf", "fvtbta3", "fvts7pm", "fvwjrnu", "fvz6hio", "fvzb1t4"], "archived": ["frvn85n", "fs1k051", "fs24003", "fs4k5hb", "fsoogy2", "fsp6spy", "fv4fthf", "fvdvy04", "fvf4uik", "fv90b9a", "fvi0798", "fvkh3do", "fvlgnkt"]}, "vinylcollectors": {"active": ["fvoride", "fvordbt", "fvorpse", "fvormzz", "fvortu2", "fvorz4p", "fvralhe", "fvr5i5u", "fvs5ez2", "fvswqfc", "fvta2j6", "fvtc5kn", "fvvk7mv", "fvvk4l4", "fvvvc0u", "fvwceng", "fvwnijj", "fvwpofl", "fvy3efs", "fvyd8f9", "fvyjcvw", "fvz3nb2", "fvzze8q", "fvzzab2", "fvzzpy9", "fw066f4"], "archived": ["frvjxw4", "frwh0he", "frwh2fc", "frwh4ez", "frwhd7k", "frwh9fl", "frwhhfl", "frwhj2e", "frwhyi5", "frwi0za", "frximix", "frydafr", "fs9kv5h", "fs9uhp5", "fs91p4z", "fsbwrkz", "fsdqinl", "fsk0pxj", "fsk0o7j", "fsk0te5", "fsqx3bx", "fsrzpvd", "fssm9bz", "fstla84", "fstlbwu", "fsw9zsn", "fswafff", "fswe4go", "fsx6mpw", "fsx6tj1", "fsx77qm", "fsx75w3", "fsx7eq2", "fsx7qi0", "fsx7rok", "fsx7ubr", "fsx7y0d", "fsx82s6", "fsxxbra", "ft0hddu", "ft9567f", "ftfopp4", "ftg4wrq", "fti9ljb", "fti9n8u", "fti9pn2", "ftif211", "ftitixi", "ftkwjfn", "ftlev8w", "ftlh0oe", "ftpwkb8", "ftpwncu", "fuli48i", "funso7d", "funx168", "fux44a7", "fuy4hdf", "fuy3jaj", "fuy4g1p", "fuy3bid", "fuy3sw8", "fuy330p", "fuvi2zf", "fuy3fyq", "fuy37kw", "fuy3p6t", "fuy4pea", "fuy4juz", "fuy3r1k", "fuy3yxw", "fv4dwbc", "fv1ymjp", "fuvi0tk", "fux5q8k", "fv158ke", "fuy40gc", "fuy424e", "fux3fyk", "fuy4h7v", "fuy43pb", "fuy4imk", "fuy4e12", "fvdf4fc", "fvdk3d6", "fv84qv9", "fvarqsr", "fvd04re", "fvd0dt6", "fvd7y6l", "fvdf63y", "fvdjzfe", "fvdk5py", "fvdx1fd", "fvfkauk", "fvfxgq9", "fvh28m2", "fvh276c", "fvhwc0g", "fvljbd7"]}, "funkoppopmod": {"active": [], "archived": []}, "disneypinswap": {"active": [], "archived": ["fspf8sm", "fve76hy"]}, "ecigclassifieds": {"active": ["fvnkzf9", "fvnr637", "fvnrm46", "fvo710w", "fvofy1x", "fvqaqm4", "fvs0agw", "fvs98b4", "fvsy9sk", "fvx0iu4", "fvyda7k", "fvzdll8", "fvzpck7", "fw00gfb", "fw09roo", "fw0dn66"], "archived": ["fs9tkc1", "fsldopg", "ft0jrle", "ftb4zrv", "ftf1qc5", "ftf2yle", "ftjvb04", "ftq013p", "fum5upk", "fv3d50g", "fuu1nzx", "fv3jk2q", "fv48zta", "fuy27ot", "fv4onte", "fv6ee02", "fverr3w", "fv6lu06", "fvka8bg"]}}